{
  "SignIn": "Кіру",
  "SingUp": "Тіркелу",
  "Market": "Базар",
  "HeroTitle": "Криптовалюталардың барлық артықшылықтарын пайдаланыңыз",
  "HeroSubtitle" : "Мүмкіншілікті алмастырыңыз",
  "In": "ішінде",
  "Buy": "сатып алу",
  "PickTitle": "MEGA — үздік таңдау",
  "Picktext1": "алмастыруға болатын токендер саны",
  "PickSubtext1": "15+",
  "Picktext2": "жоғары",
  "PickSubtext2": "спрэдтер",
  "Picktext3": "жасырын төлем жоқ",
  "PickSubtext3": "Көрсетілген комиссиялар.",
  "Picktext4": "Әлемдік AML және KYC стандарттарына сай",
  "PickSubtext4": "Толық жобалау.",
  "Picktext5": "мүмкіндіктер туралы қалайлы көрсетілгені",
  "PickSubtext5": "450+",
  "Picktext6": "волатильділік бақылауы",
  "PickSubtext6": "Үздік",
  "Picktext7": "техникалық қолдау",
  "PickSubtext7": "Жылдам жауап беру",
  "Picktext8": "шифрланған пішімде сақталады",
  "StartTitle": "Криптовалюталар жетістікті:",
  "StartTSubtitle": "300 000+ пайдаланушыдан тұратын біздің қоғамға қосылыңыз",
  "StartStep1": "Аккаунт жасаңыз",



  "StartStep2": "Аккаунтты толтыру",
  "StartStep3": "Жаңа жасау",
  "NameOfCrypt": "Криптовалютаның атауын енгізіңіз",
  "DateCreated": "Аккаунттың жасалған күні:",
  "DelBtn": "Аккаунтты жою",
  "RepeatPass": "Құпия сөзді қайталаңыз",
  "UserDel": "Пайдаланушы жойылды",
  "Links": "Пайдалы сілтемелер",
  "News": "Жаңалықтар порталы",
  "TA": "Техникалық талдау",
  "Graph": "Базар диаграммалары",
  "Binance": "Binance",
  "Bybit": "Bybit",
  "Kraken": "Kraken",
  "Social": "Біз әлеуметтік желілерде",
  "Date": "күні",
  "Wallet": "көшелек",
  "Crypt": "криптоактив",
  "Count": "саны",
  "Send": "жіберу",
  "CountToSend": "Жіберілетін криптовалютаның санын енгізіңіз",
  "WalletToSend": "Көшелекті төмендегі тереңіз",
  "Done": "Қаржы сәтті төленді",
  "FNameErr": "Тегі өрісі бос болмауы тиіс",
  "SNameErr": "Құпия сөз бос болмауы тиіс",
  "LNameErr": "Телефон нөмірі бос болмауы тиіс",
  "UNameErr": "Пайдаланушы аты бос болмауы тиіс",
  "AgeErr": "Жасы белгіленмеген жол болмасын",
  "O1": "Пайдаланушы аты 5-тен үлкен болуы тиіс",
  "O2": "Пайдаланушы аты 55-тен кіші болуы тиіс",
  "O3": "Тегі 2-ден 25 символға дейін ұзын болуы тиіс",
  "O4": "Аты 2-ден 25 символға дейін ұзын болуы тиіс",



  "O5": "Отчество 2 символдан үлкен және 25 символдан аз болуы керек",
  "O6": "Туылған жылы 18-ден 100-ге дейін болуы керек",
  "UName": "Пайдаланушы аты:",
  "SName": "Тегі:",
  "Lname": "Аты:",
  "FName": "Әкесінің аты:",
  "DB": "Туылған күні:",
  "Ages": "Сіздің жасыңыз:",
  "Canc": "Болдырмау",
  "Ed": "Өзгерту",
  "Save": "өзгерістерді сақтау",
  "LogOrPass": "Жарамсыз логин немесе пароль",
  "PassText": "Құпия сөз жолы бос болмауы керек",
  "CurpassError": "Құпия сөз: 12-ден кем және 25-тен көп символдарға ие болуы, немесе бір жақша әріп, бір кіші әріп, немесе бір нөмір немесе бір арнайы символ болуы керек",
  "RepeatpassError": "Құпия сөздер сәйкес келуі керек",
  "CPass": "Ағымдағы құпия сөз:",
  "NPass": "Жаңа құпия сөз:",
  "RNPass": "Жаңа құпия сөзді қайталау:",
  "Of": "ның",
  "InB": "ішіне",
  "ToPay": "Төлем:",
  "CardNum": "Карта нөмірі",
  "CardName": "Турақтықтың аты",
  "Be": "Аяқталады",
  "CVC/CVV": "Соңғы 3 немесе 4 цифр",
  "BuyDone": "Транзакция сәтті аяқталды",
  "BuyErr": "Транзакция қатесі",
  "ToProfile": "Профильге өту",
  "ToMarket": "Сауда бетіне өту",
  "Person": "Жеке ақпарат",
  "Private": "Конфиденциальді деректер",
  "Briefcase": "Қаражат",
  "Output": "Криптовалютадан шығару",
  "History": "Транзакциялар тарихы",
  "Details": "Аккаунт толық мәліметтері",
  "EmaErr": "Email бос болмауы керек",
  "PassErr": "Құпия сөз бос болмауы керек",
  "TelErr": "Телефон бос болмауы керек",
  "RPassErr": "Қайталап енгізу керек құпия сөз бос болмауы керек",


  "LogOut": "Аккаунтан шығу",
  "PersonBtn": "Жеке кабинет",
  "UErr": "Пайдаланушы аты бос болмауы керек",
  "EmaInCor": "Қате email",
  "TelInCor": "Қате телефон нөмірі",
  "UN1": "Пайдаланушы аті 5-тен үлкен болуы керек",
  "UN2": "Пайдаланушы аті 55-тен аз болуы керек",
  "UN3": "Пайдаланушы аті 55-тен аз болуы керек",
  "PRRERR": "Құпия сөзде кем дегенде 12, ең әрі 25 белгінің ішінде болуы керек, немесе бір үлкен әрі кіші әрі сандық немесе бір арнайы белгі болуы керек",
  "RPASSER": "Құпия сөздер сәйкес келмейді",
  "PassInCor": "Құпия сөзде кем дегенде 12, ең әрі 25 белгі болуы керек",
  "Em": "Пошта",
  "Log": "Логин",
  "Tel": "Телефон нөмірі",
  "RPRR": "Құпия сөзді қайталау",
  "Pass": "Құпия сөз",
  "Sign1": "Кіру",
  "Register": "Тіркелу",
  "AlreadyRegister": "Мұндай пайдаланушы бар",
  "DoneREgister": "Сіз сәтті тіркелдіңіз",
  "Sign2": "Тіркелу",
  "Social": "Біз әлеуметтік желілерде"
}